{
  "sections": {
    "banner": {
      "type": "main-collection-banner",
      "settings": {
        "show_collection_description": true,
        "show_collection_image": false,
        "color_scheme": "scheme-1"
      }
    },
    "multirow_8gzaUt": {
      "type": "multirow",
      "blocks": {
        "row_zfzKdV": {
          "type": "row",
          "settings": {
            "image": "shopify:\/\/shop_images\/sylvie.jpg",
            "caption": "Sylvie",
            "heading": "The Fearless One",
            "text": "",
            "button_label": "Add to Cart",
            "button_link": "shopify:\/\/products\/sylvie"
          }
        },
        "row_Lx7agz": {
          "type": "row",
          "settings": {
            "image": "shopify:\/\/shop_images\/emily.jpg",
            "caption": "Emily",
            "heading": "The Mastermind",
            "text": "",
            "button_label": "Add to Cart",
            "button_link": "shopify:\/\/products\/emily"
          }
        },
        "row_UzMdyn": {
          "type": "row",
          "settings": {
            "image": "shopify:\/\/shop_images\/madeline.jpg",
            "caption": "Madeline",
            "heading": "In a Hurry",
            "text": "",
            "button_label": "Get Yours",
            "button_link": "shopify:\/\/products\/madeline"
          }
        },
        "row_XpBqyE": {
          "type": "row",
          "settings": {
            "image": "shopify:\/\/shop_images\/camille.jpg",
            "caption": "Camille",
            "heading": "Effortless Savoir Faire",
            "text": "",
            "button_label": "Say No More",
            "button_link": "shopify:\/\/products\/camille"
          }
        }
      },
      "block_order": [
        "row_zfzKdV",
        "row_Lx7agz",
        "row_UzMdyn",
        "row_XpBqyE"
      ],
      "settings": {
        "image_height": "small",
        "desktop_image_width": "large",
        "heading_size": "h1",
        "text_style": "body",
        "button_style": "primary",
        "desktop_content_position": "middle",
        "desktop_content_alignment": "right",
        "image_layout": "alternate-left",
        "section_color_scheme": "",
        "row_color_scheme": "",
        "mobile_content_alignment": "left",
        "padding_top": 36,
        "padding_bottom": 36
      }
    },
    "product-grid": {
      "type": "main-collection-product-grid",
      "settings": {
        "products_per_page": 16,
        "columns_desktop": 3,
        "color_scheme": "",
        "image_ratio": "portrait",
        "image_shape": "default",
        "show_secondary_image": true,
        "show_vendor": true,
        "show_rating": false,
        "enable_quick_add": true,
        "enable_filtering": true,
        "filter_type": "horizontal",
        "enable_sorting": true,
        "columns_mobile": "2",
        "padding_top": 36,
        "padding_bottom": 36
      }
    }
  },
  "order": [
    "banner",
    "multirow_8gzaUt",
    "product-grid"
  ]
}
